<?xml version="1.0" encoding="UTF-8" standalone="no"?>
<!DOCTYPE score-partwise PUBLIC "-//Recordare//DTD MusicXML 4.0 Partwise//EN" "http://www.musicxml.org/dtds/partwise.dtd">
<score-partwise version="4.0">
  <work>
    <work-title>Nested Tuplets Middle</work-title>
  </work>
  <movement-title>Bloc 1</movement-title>
  <identification>
    <encoding>
      <software>Dorico 5.1.60.2187</software>
      <encoding-date>2024-11-14</encoding-date>
      <supports type="yes" element="print" attribute="new-system" value="yes"/>
      <supports type="yes" element="print" attribute="new-page" value="yes"/>
      <supports type="yes" element="accidental"/>
      <supports type="yes" element="beam"/>
      <supports type="yes" element="stem"/>
    </encoding>
  </identification>
  <defaults>
    <scaling>
      <millimeters>6.99911</millimeters>
      <tenths>40</tenths>
    </scaling>
    <page-layout>
      <page-height>1695.56</page-height>
      <page-width>1197.58</page-width>
      <page-margins type="both">
        <left-margin>84.6774</left-margin>
        <right-margin>84.6774</right-margin>
        <top-margin>84.6774</top-margin>
        <bottom-margin>84.6774</bottom-margin>
      </page-margins>
    </page-layout>
    <music-font font-family="Bravura" font-size="19.84"/>
    <word-font font-family="Academico" font-size="9.92"/>
  </defaults>
  <credit page="1">
    <credit-type>part name</credit-type>
    <credit-words font-family="Academico" font-size="14" justify="left" valign="top" enclosure="rectangle" default-x="83.75" default-y="1598.12" xml:space="preserve">Voice 1</credit-words>
  </credit>
  <credit page="1">
    <credit-type>title</credit-type>
    <credit-words font-family="Academico" font-size="20" justify="center" valign="middle" default-x="593.75" default-y="1522.5" xml:space="preserve">Projet sans titre 1</credit-words>
  </credit>
  <part-list>
    <score-part id="P1">
      <part-name print-object="no">Voice 1</part-name>
      <part-name-display print-object="no">
        <display-text/>
      </part-name-display>
      <part-abbreviation print-object="no">V. 1</part-abbreviation>
      <part-abbreviation-display print-object="no">
        <display-text/>
      </part-abbreviation-display>
      <score-instrument id="instrument-1">
        <instrument-name>Voice 1</instrument-name>
        <instrument-sound>voice.vocals</instrument-sound>
      </score-instrument>
    </score-part>
  </part-list>
  <part id="P1">
    <measure number="1">
      <print>
        <system-layout>
          <system-margins>
            <left-margin>60</left-margin>
            <right-margin>0</right-margin>
          </system-margins>
          <top-system-distance>241.875</top-system-distance>
        </system-layout>
      </print>
      <attributes>
        <divisions>60</divisions>
        <key number="1">
          <fifths>0</fifths>
          <mode>major</mode>
        </key>
        <time>
          <beats>4</beats>
          <beat-type>4</beat-type>
        </time>
        <staves>1</staves>
        <clef number="1">
          <sign>G</sign>
          <line>2</line>
        </clef>
      </attributes>
      <note>
        <pitch>
          <step>G</step>
          <octave>4</octave>
        </pitch>
        <duration>60</duration>
        <voice>1</voice>
        <type>quarter</type>
        <stem>up</stem>
        <staff>1</staff>
      </note>
      <note>
        <pitch>
          <step>A</step>
          <octave>4</octave>
        </pitch>
        <duration>24</duration>
        <voice>1</voice>
        <type>eighth</type>
        <time-modification>
          <actual-notes>5</actual-notes>
          <normal-notes>4</normal-notes>
          <normal-type>eighth</normal-type>
        </time-modification>
        <stem>up</stem>
        <staff>1</staff>
        <beam number="1">begin</beam>
        <notations>
          <tuplet type="start" bracket="yes" number="1">
            <tuplet-actual>
              <tuplet-number>5</tuplet-number>
              <tuplet-type>eighth</tuplet-type>
            </tuplet-actual>
            <tuplet-normal>
              <tuplet-number>4</tuplet-number>
              <tuplet-type>eighth</tuplet-type>
            </tuplet-normal>
          </tuplet>
        </notations>
      </note>
      <note>
        <pitch>
          <step>B</step>
          <octave>4</octave>
        </pitch>
        <duration>24</duration>
        <voice>1</voice>
        <type>eighth</type>
        <time-modification>
          <actual-notes>5</actual-notes>
          <normal-notes>4</normal-notes>
          <normal-type>eighth</normal-type>
        </time-modification>
        <stem>up</stem>
        <staff>1</staff>
        <beam number="1">end</beam>
      </note>
      <note>
        <pitch>
          <step>C</step>
          <octave>5</octave>
        </pitch>
        <duration>16</duration>
        <voice>1</voice>
        <type>eighth</type>
        <time-modification>
          <actual-notes>15</actual-notes>
          <normal-notes>8</normal-notes>
        </time-modification>
        <stem>down</stem>
        <staff>1</staff>
        <beam number="1">begin</beam>
        <notations>
          <tuplet type="start" bracket="yes" number="2">
            <tuplet-actual>
              <tuplet-number>3</tuplet-number>
              <tuplet-type>eighth</tuplet-type>
            </tuplet-actual>
            <tuplet-normal>
              <tuplet-number>2</tuplet-number>
              <tuplet-type>eighth</tuplet-type>
            </tuplet-normal>
          </tuplet>
        </notations>
      </note>
      <note>
        <pitch>
          <step>D</step>
          <octave>5</octave>
        </pitch>
        <duration>16</duration>
        <voice>1</voice>
        <type>eighth</type>
        <time-modification>
          <actual-notes>15</actual-notes>
          <normal-notes>8</normal-notes>
        </time-modification>
        <stem>down</stem>
        <staff>1</staff>
        <beam number="1">continue</beam>
      </note>
      <note>
        <pitch>
          <step>E</step>
          <octave>5</octave>
        </pitch>
        <duration>16</duration>
        <voice>1</voice>
        <type>eighth</type>
        <time-modification>
          <actual-notes>15</actual-notes>
          <normal-notes>8</normal-notes>
        </time-modification>
        <stem>down</stem>
        <staff>1</staff>
        <beam number="1">end</beam>
        <notations>
          <tuplet type="stop" bracket="yes" number="2"/>
        </notations>
      </note>
      <note>
        <pitch>
          <step>F</step>
          <octave>5</octave>
        </pitch>
        <duration>24</duration>
        <voice>1</voice>
        <type>eighth</type>
        <time-modification>
          <actual-notes>5</actual-notes>
          <normal-notes>4</normal-notes>
          <normal-type>eighth</normal-type>
        </time-modification>
        <stem>down</stem>
        <staff>1</staff>
        <notations>
          <tuplet type="stop" bracket="yes" number="1"/>
        </notations>
      </note>
      <note>
        <pitch>
          <step>G</step>
          <octave>5</octave>
        </pitch>
        <duration>60</duration>
        <voice>1</voice>
        <type>quarter</type>
        <stem>down</stem>
        <staff>1</staff>
      </note>
      <barline location="right">
        <bar-style>light-heavy</bar-style>
      </barline>
    </measure>
  </part>
</score-partwise>
